optimalportfolios/__init__.py
optimalportfolios/config.py
optimalportfolios/covar_estimation/__init__.py
optimalportfolios/covar_estimation/config.py
optimalportfolios/covar_estimation/covar_estimator.py
optimalportfolios/covar_estimation/current_covar.py
optimalportfolios/covar_estimation/rolling_covar.py
optimalportfolios/covar_estimation/utils.py
optimalportfolios/examples/crypto_allocation/article_figures.py
optimalportfolios/examples/crypto_allocation/backtest_portfolios_for_article.py
optimalportfolios/examples/crypto_allocation/load_prices.py
optimalportfolios/examples/crypto_allocation/perf_crypto_portfolios.py
optimalportfolios/examples/crypto_allocation/README.md
optimalportfolios/examples/lasso_covar_estimation.py
optimalportfolios/examples/lasso_estimation.py
optimalportfolios/examples/long_short_optimisation.py
optimalportfolios/examples/multi_covar_estimation_backtest.py
optimalportfolios/examples/multi_optimisers_backtest.py
optimalportfolios/examples/optimal_portfolio_backtest.py
optimalportfolios/examples/parameter_sensitivity_backtest.py
optimalportfolios/examples/solve_risk_budgets_balanced_portfolio.py
optimalportfolios/examples/solvers/carra_mixture.py
optimalportfolios/examples/solvers/max_diversification.py
optimalportfolios/examples/solvers/max_sharpe.py
optimalportfolios/examples/solvers/min_variance.py
optimalportfolios/examples/solvers/risk_parity.py
optimalportfolios/examples/solvers/target_return.py
optimalportfolios/examples/solvers/tracking_error.py
optimalportfolios/examples/sp500_minvar.py
optimalportfolios/examples/universe.py
optimalportfolios/lasso/__init__.py
optimalportfolios/lasso/lasso_model_estimator.py
optimalportfolios/local_path.py
optimalportfolios/optimization/__init__.py
optimalportfolios/optimization/constraints.py
optimalportfolios/optimization/solvers/__init__.py
optimalportfolios/optimization/solvers/carra_mixure.py
optimalportfolios/optimization/solvers/max_diversification.py
optimalportfolios-3.3.8.dist-info/LICENSE.txt
optimalportfolios-3.3.8.dist-info/METADATA
optimalportfolios-3.3.8.dist-info/WHEEL
optimalportfolios-3.3.8.dist-info/RECORD
