Metadata-Version: 2.3
Name: optimalportfolios
Version: 3.3.8
Summary: Simulation and backtesting of optimal portfolios
License: LICENSE.txt
Keywords: quantitative,investing,portfolio optimization,systematic strategies,volatility
Author: Artur Sepp
Author-email: artursepp@gmail.com
Maintainer: Artur Sepp
Maintainer-email: artursepp@gmail.com
Requires-Python: >=3.8
Classifier: Development Status :: 4 - Beta
Classifier: Environment :: Console
Classifier: Intended Audience :: Financial and Insurance Industry
Classifier: Intended Audience :: Science/Research
Classifier: License :: OSI Approved :: MIT License
Classifier: License :: Other/Proprietary License
Classifier: Natural Language :: English
Classifier: Operating System :: OS Independent
Classifier: Programming Language :: Python :: 3
Classifier: Programming Language :: Python :: 3.8
Classifier: Programming Language :: Python :: 3.9
Classifier: Programming Language :: Python :: 3.10
Classifier: Programming Language :: Python :: 3.11
Classifier: Programming Language :: Python :: 3.12
Classifier: Programming Language :: Python :: 3.13
Classifier: Programming Language :: Python :: 3 :: Only
Classifier: Topic :: Office/Business :: Financial :: Investment
Requires-Dist: cvxpy (>=1.3.2)
Requires-Dist: matplotlib (>=3.8.3)
Requires-Dist: numba (>=0.59.0)
Requires-Dist: numpy (>=1.26.4)
Requires-Dist: pandas (>=2.2.0)
Requires-Dist: psycopg2 (>=2.9.5)
Requires-Dist: pybloqs (>=1.2.13)
Requires-Dist: qis (>=2.1.1)
Requires-Dist: quadprog (>=0.1.13)
Requires-Dist: scikit_learn (>=1.3.0)
Requires-Dist: scipy (>=1.12.0)
Requires-Dist: seaborn (>=0.13.2)
Requires-Dist: setuptools (>=69.1.1)
Requires-Dist: yfinance (>=0.2.37)
Project-URL: Documentation, https://github.com/ArturSepp/OptimalPortfolios
Project-URL: Issues, https://github.com/ArturSepp/OptimalPortfolios/issues
Project-URL: Personal website, https://artursepp.com
Project-URL: Repository, https://github.com/ArturSepp/OptimalPortfolios
